annzoo/__init__.py
annzoo/ann.py
annzoo/ann_service.py
annzoo/faiss.py
ANNZOO-2021.2.5.19.21.41.dist-info/LICENSE
ANNZOO-2021.2.5.19.21.41.dist-info/METADATA
ANNZOO-2021.2.5.19.21.41.dist-info/WHEEL
ANNZOO-2021.2.5.19.21.41.dist-info/entry_points.txt
ANNZOO-2021.2.5.19.21.41.dist-info/top_level.txt
ANNZOO-2021.2.5.19.21.41.dist-info/RECORD
