Metadata-Version: 2.1
Name: ANNZOO
Version: 2021.2.5.19.21.41
Summary: description
Home-page: https://github.com/Jie-Yuan/ANNZOO
Author: YuanJie
Author-email: 313303303@qq.com
Maintainer: JieYuan
Maintainer-email: 313303303@qq.com
License: Apache
Keywords: tool wheel,yuanjie,utils
Platform: all
Classifier: Operating System :: OS Independent
Classifier: Intended Audience :: Developers
Classifier: License :: OSI Approved :: MIT License
Classifier: Programming Language :: Python
Classifier: Programming Language :: Python :: Implementation
Requires-Dist: pymilvus
